cupy_fft_match/__init__.py
cupy_fft_match/match_arr.py
cupy_fft_match-0.0.0.dist-info/licenses/LICENSE
cupy_fft_match-0.0.0.dist-info/METADATA
cupy_fft_match-0.0.0.dist-info/WHEEL
cupy_fft_match-0.0.0.dist-info/top_level.txt
cupy_fft_match-0.0.0.dist-info/RECORD
