Metadata-Version: 2.4
Name: cupy_fft_match
Version: 0.0.0
Summary: A fast fuzzy matching algorithm based on FFT.
Author-email: GGN_2015 <neko@jlulug.org>
License: MIT License
Requires-Python: >=3.10
License-File: LICENSE
Requires-Dist: cupy
Dynamic: license-file
